COPYING
ChangeLog
MANIFEST.in
NEWS
README
setup.py
doc/Building_Binaries.adoc
doc/osx-compiling.adoc
man/yubioath-cli.1.xml
man/yubioath-gui.1.adoc
man/yubioath.1.adoc
qt_resources/calc.png
qt_resources/copy.png
qt_resources/qr.png
qt_resources/yubioath.png
resources/installer_bg.png
resources/linux-patch-ccid
resources/osx-installer.pkgproj
resources/win-installer.nsi
resources/yubioath-desktop.icns
resources/yubioath-desktop.ico
resources/yubioath-desktop.png
resources/yubioath.desktop
resources/yubioath.xpm
yubioath/__init__.py
yubioath/cli/__init__.py
yubioath/cli/__main__.py
yubioath/cli/controller.py
yubioath/cli/keystore.py
yubioath/cli/unlocker.py
yubioath/core/__init__.py
yubioath/core/ccid.py
yubioath/core/controller.py
yubioath/core/exc.py
yubioath/core/legacy_ccid.py
yubioath/core/legacy_otp.py
yubioath/core/standard.py
yubioath/core/utils.py
yubioath/gui/__init__.py
yubioath/gui/__main__.py
yubioath/gui/ccid.py
yubioath/gui/ccid_poll.py
yubioath/gui/controller.py
yubioath/gui/keystore.py
yubioath/gui/messages.py
yubioath/gui/qrdecode.py
yubioath/gui/qrparse.py
yubioath/gui/qt_resources.py
yubioath/gui/view/__init__.py
yubioath/gui/view/add_cred.py
yubioath/gui/view/add_cred_legacy.py
yubioath/gui/view/ccid_disabled.py
yubioath/gui/view/codes.py
yubioath/gui/view/get_password.py
yubioath/gui/view/set_password.py
yubioath/gui/view/settings.py
yubioath/gui/view/systray.py
yubioath/yubicommon/__init__.py
yubioath/yubicommon/compat.py
yubioath/yubicommon/ctypes/__init__.py
yubioath/yubicommon/ctypes/libloader.py
yubioath/yubicommon/qt/__init__.py
yubioath/yubicommon/qt/classes.py
yubioath/yubicommon/qt/osx.py
yubioath/yubicommon/qt/settings.py
yubioath/yubicommon/qt/utils.py
yubioath/yubicommon/qt/worker.py
yubioath/yubicommon/setup/__init__.py
yubioath/yubicommon/setup/exe.py
yubioath/yubicommon/setup/pyinstaller_spec.py
yubioath/yubicommon/setup/qt.py
yubioath_desktop.egg-info/PKG-INFO
yubioath_desktop.egg-info/SOURCES.txt
yubioath_desktop.egg-info/dependency_links.txt
yubioath_desktop.egg-info/entry_points.txt
yubioath_desktop.egg-info/requires.txt
yubioath_desktop.egg-info/top_level.txt