Metadata-Version: 1.1
Name: yubioath-desktop
Version: 3.0.0
Summary: Graphical interface for displaying OATH codes with a Yubikey
Home-page: https://github.com/Yubico/yubioath-desktop
Author: Yubico Open Source Maintainers
Author-email: ossmaint@yubico.com
License: GPLv3+
Platform: UNKNOWN
Classifier: License :: OSI Approved :: GNU General Public License v3 or later (GPLv3+)
Classifier: Operating System :: OS Independent
Classifier: Programming Language :: Python
Classifier: Development Status :: 4 - Beta
Classifier: Environment :: X11 Applications :: Qt
Classifier: Intended Audience :: End Users/Desktop
Classifier: Topic :: Security :: Cryptography
Classifier: Topic :: Utilities
